odoo/addons/website_sale_helm/LICENSE
odoo/addons/website_sale_helm/README.rst
odoo/addons/website_sale_helm/__init__.py
odoo/addons/website_sale_helm/__manifest__.py
odoo/addons/website_sale_helm/data/data.xml
odoo/addons/website_sale_helm/images/screen.png
odoo/addons/website_sale_helm/models/__init__.py
odoo/addons/website_sale_helm/models/sale_order.py
odoo/addons/website_sale_helm/static/description/icon.png
odoo/addons/website_sale_helm/static/description/index.html
odoo/addons/website_sale_helm/tests/TEST_INSTRUCTIONS.rst
odoo/addons/website_sale_helm/views/website_templates.xml
odoo_addon_website_sale_helm-18.0.1.0.0.dist-info/METADATA
odoo_addon_website_sale_helm-18.0.1.0.0.dist-info/WHEEL
odoo_addon_website_sale_helm-18.0.1.0.0.dist-info/top_level.txt
odoo_addon_website_sale_helm-18.0.1.0.0.dist-info/RECORD
